Workbook

Sheet RawData
A1: Company | B1: Bank | C1: Role | D1: Source | E1: Document | F1: Appointment
A2: AutoAI (Nanjing) Technology Co., Ltd. | B2: CLSA Limited | C2: Sponsor-Overall Coordinator | D2: https://www1.hkexnews.hk/app/sehk/2025/107497/documents/sehk25071000873.pdf | E2: OC Announcement - 10/07/2025 | F2: 27 June 2025
A3: AutoAI (Nanjing) Technology Co., Ltd. | B3: CMB International Capital Limited | C3: Overall Coordinator | D3: https://www1.hkexnews.hk/app/sehk/2025/107497/documents/sehk25071000873.pdf | E3: OC Announcement - 10/07/2025 | F3: 10 July 2025
A4: AutoAI (Nanjing) Technology Co., Ltd. | B4: SBI China Capital Financial Services Limited | C4: Overall Coordinator | D4: https://www1.hkexnews.hk/app/sehk/2025/107497/documents/sehk25071000873.pdf | E4: OC Announcement - 10/07/2025 | F4: 10 July 2025
A5: Qingdao Gon Technology Co., Ltd. | B5: China Merchants Securities (HK) Co., Limited | C5: Sponsor-Overall Coordinator | D5: https://www1.hkexnews.hk/app/sehk/2025/107485/documents/sehk25071000925.pdf | E5: OC Announcement - 10/07/2025 | F5: 26 June 2025
A6: Qingdao Gon Technology Co., Ltd. | B6: China International Capital Corporation Hong Kong Securities Limited | C6: Overall Coordinator | D6: https://www1.hkexnews.hk/app/sehk/2025/107485/documents/sehk25071000925.pdf | E6: OC Announcement - 10/07/2025 | F6: 10 July 2025
A7: Qingdao Gon Technology Co., Ltd. | B7: CLSA Limited | C7: Overall Coordinator | D7: https://www1.hkexnews.hk/app/sehk/2025/107485/documents/sehk25071000925.pdf | E7: OC Announcement - 10/07/2025 | F7: 10 July 2025
A8: Intsig Information Co., Ltd. | B8: China International Capital Corporation Hong Kong Securities Limited | C8: Sponsor-Overall Coordinator | D8: https://www1.hkexnews.hk/app/sehk/2025/107479/documents/sehk25070900940.pdf | E8: OC Announcement - 09/07/2025 | F8: 26 June 2025
A9: Intsig Information Co., Ltd. | B9: CLSA Limited | C9: Overall Coordinator | D9: https://www1.hkexnews.hk/app/sehk/2025/107479/documents/sehk25070900940.pdf | E9: OC Announcement - 09/07/2025 | F9: 9 July 2025
A10: Shanghai Longcheer Technology Co., Ltd. | B10: Citigroup Global Markets Asia Limited | C10: Sponsor-Overall Coordinator | D10: https://www1.hkexnews.hk/app/sehk/2025/107505/documents/sehk25070900720.pdf | E10: OC Announcement - 09/07/2025 | F10: 27 June 2025
A11: Shanghai Longcheer Technology Co., Ltd. | B11: Haitong International Securities Company Limited | C11: Sponsor-Overall Coordinator | D11: https://www1.hkexnews.hk/app/sehk/2025/107505/documents/sehk25070900720.pdf | E11: OC Announcement - 09/07/2025 | F11: 27 June 2025
A12: Shanghai Longcheer Technology Co., Ltd. | B12: Guotai Junan Securities (Hong Kong) Limited | C12: Sponsor-Overall Coordinator | D12: https://www1.hkexnews.hk/app/sehk/2025/107505/documents/sehk25070900720.pdf | E12: OC Announcement - 09/07/2025 | F12: 27 June 2025
... A129: Delton Technology (Guangzhou) Inc. | B129: Huatai Financial Holdings (Hong Kong) Limited | C129: Overall Coordinator | D129: https://www1.hkexnews.hk/app/sehk/2025/107433/documents/sehk25062500424.pdf | E129: OC Announcement - 25/06/2025 | F129: 25 June 2025
A130: Immvira Bioscience Inc. | B130: Citigroup Global Markets Asia Limited | C130: Overall Coordinator | E130: OC Announcement - 25/06/2025 | F130: 25 June 2025
A131: Immvira Bioscience Inc. | B131: China International Capital Corporation Hong Kong Securities Limited | C131: Overall Coordinator | D131: https://www1.hkexnews.hk/app/sehk/2025/107478/documents/sehk25062502251.pdf | E131: OC Announcement - 25/06/2025 | F131: 25 June 2025
A132: GigaDevice Semiconductor Inc. | B132: China International Capital Corporation Hong Kong Securities Limited | C132: Overall Coordinator | D132: https://www1.hkexnews.hk/app/sehk/2025/107462/documents/sehk25061901349.pdf | E132: OC Announcement - 23/06/2025 | F132: 23 June 2025
A133: GigaDevice Semiconductor Inc. | B133: Huatai Financial Holdings (Hong Kong) Limited | C133: Overall Coordinator | D133: https://www1.hkexnews.hk/app/sehk/2025/107462/documents/sehk25061901349.pdf | E133: OC Announcement - 23/06/2025 | F133: 23 June 2025
A134: PPLabs Technology Limited | B134: ICBC International Securities Limited | C134: Overall Coordinator | D134: https://www1.hkexnews.hk/app/sehk/2025/107464/documents/sehk25062001211.pdf | E134: OC Announcement - 20/06/2025 | F134: 20 June 2025
A135: PPLabs Technology Limited | B135: Shenwan Hongyuan Securities (H.K.) Limited | C135: Overall Coordinator | D135: https://www1.hkexnews.hk/app/sehk/2025/107464/documents/sehk25062001211.pdf | E135: OC Announcement - 20/06/2025 | F135: 20 June 2025
A136: Gpixel Changchun Microelectronics Inc. | B136: CLSA Limited | C136: Overall Coordinator | D136: https://www1.hkexnews.hk/app/sehk/2025/107461/documents/sehk25061901057.pdf | E136: OC Announcement - 19/06/2025 | F136: 19 June 2025
A137: Gpixel Changchun Microelectronics Inc. | B137: Guotai Junan Securities (Hong Kong) Limited | C137: Overall Coordinator | D137: https://www1.hkexnews.hk/app/sehk/2025/107461/documents/sehk25061901057.pdf | E137: OC Announcement - 19/06/2025 | F137: 19 June 2025
A138: Shanghai Able Digital Science&Tech Co., Ltd. | B138: ABCI Capital Limited | C138: Sole Overall Coordinator | D138: https://www1.hkexnews.hk/app/sehk/2025/107458/documents/sehk25061801700.pdf | E138: OC Announcement - 18/06/2025 | F138: 17 June 2025
A139: Beijing Haizhi Technology Group Co., Ltd. | B139: CMB International Capital Limited | C139: Overall Coordinator | D139: https://www1.hkexnews.hk/app/sehk/2025/107452/documents/sehk25061701306.pdf | E139: OC Announcement - 17/06/2025 | F139: 17 June 2025
A140: Beijing Haizhi Technology Group Co., Ltd. | B140: BOCI Asia Limited | C140: Overall Coordinator | D140: https://www1.hkexnews.hk/app/sehk/2025/107452/documents/sehk25061701306.pdf | E140: OC Announcement - 17/06/2025 | F140: 17 June 2025
A141: Beijing Haizhi Technology Group Co., Ltd. | B141: Shenwan Hongyuan Securities (H.K.) Limited | C141: Overall Coordinator | D141: https://www1.hkexnews.hk/app/sehk/2025/107452/documents/sehk25061701306.pdf | E141: OC Announcement - 17/06/2025 | F141: 17 June 2025
A142: EpimAb Biotherapeutics Inc. | B142: CLSA Limited | C142: Overall Coordinator | D142: https://www1.hkexnews.hk/app/sehk/2025/107454/documents/sehk25061701408.pdf | E142: OC Announcement - 17/06/2025 | F142: 17 June 2025
... A195: Worldwide Logistics Holding Inc. | B195: China Industrial Securities International Capital Limited | C195: Overall Coordinator | D195: https://www1.hkexnews.hk/app/sehk/2025/107399/documents/sehk25060900807.pdf | E195: OC Announcement - 09/06/2025 | F195: 9 June 2025
A196: Switchbot (Shenzhen) Co., Ltd. | B196: Guotai Junan Securities (Hong Kong) Limited | C196: Sponsor-Overall Coordinator | D196: https://www1.hkexnews.hk/app/sehk/2025/107426/documents/sehk25060800138.pdf | E196: OC Announcement - 08/06/2025 | F196: 45816
A197: Switchbot (Shenzhen) Co., Ltd. | B197: Huatai Financial Holdings (Hong Kong) Limited | C197: Sponsor-Overall Coordinator | D197: https://www1.hkexnews.hk/app/sehk/2025/107426/documents/sehk25060800138.pdf | E197: OC Announcement - 08/06/2025 | F197: 45816
A198: Beijing Sinotau International Pharmaceutical Technology Co., Ltd. | B198: China International Capital Corporation Hong Kong Securities Limited | C198: Overall Coordinator | D198: https://www1.hkexnews.hk/app/sehk/2025/107395/documents/sehk25060601346.pdf | E198: OC Announcement - 06/06/2025 | F198: 6 June 2025
A199: Beijing Sinotau International Pharmaceutical Technology Co., Ltd. | B199: CLSA Limited | C199: Overall Coordinator | D199: https://www1.hkexnews.hk/app/sehk/2025/107395/documents/sehk25060601346.pdf | E199: OC Announcement - 06/06/2025 | F199: 6 June 2025
A200: Beijing Sinotau International Pharmaceutical Technology Co., Ltd. | B200: GF Securities (Hong Kong) Brokerage Limited | C200: Overall Coordinator | D200: https://www1.hkexnews.hk/app/sehk/2025/107395/documents/sehk25060601346.pdf | E200: OC Announcement - 06/06/2025 | F200: 6 June 2025
A201: Beijing Sinotau International Pharmaceutical Technology Co., Ltd. | B201: DBS Asia Capital Limited | C201: Overall Coordinator | D201: https://www1.hkexnews.hk/app/sehk/2025/107395/documents/sehk25060601346.pdf | E201: OC Announcement - 06/06/2025 | F201: 6 June 2025
A202: Beijing Sinotau International Pharmaceutical Technology Co., Ltd. | B202: CMB International Capital Limited | C202: Overall Coordinator | D202: https://www1.hkexnews.hk/app/sehk/2025/107395/documents/sehk25060601346.pdf | E202: OC Announcement - 06/06/2025 | F202: 6 June 2025
A203: 52TOYS Development Co., Ltd. | B203: Citigroup Global Markets Asia Limited | C203: Sponsor-Overall Coordinator | D203: https://www1.hkexnews.hk/app/sehk/2025/107389/documents/sehk25060500514.pdf | E203: OC Announcement - 05/06/2025 | F203: 22 May 2025
A204: 52TOYS Development Co., Ltd. | B204: Huatai Financial Holdings (Hong Kong) Limited | C204: Sponsor-Overall Coordinator | D204: https://www1.hkexnews.hk/app/sehk/2025/107389/documents/sehk25060500514.pdf | E204: OC Announcement - 05/06/2025 | F204: 5 June 2025
A205: 52TOYS Development Co., Ltd. | B205: GF Securities (Hong Kong) Brokerage Limited | C205: Overall Coordinator | D205: https://www1.hkexnews.hk/app/sehk/2025/107389/documents/sehk25060500514.pdf | E205: OC Announcement - 05/06/2025 | F205: 4 June 2025
A206: SANY Heavy Industry Co., Ltd. | B206: CLSA Limited | C206: Sponsor-Overall Coordinator | D206: https://www1.hkexnews.hk/app/sehk/2025/107388/documents/sehk25060502412.pdf | E206: OC Announcement - 05/06/2025 | F206: 22 May 2025
A207: SANY Heavy Industry Co., Ltd. | B207: China International Capital Corporation Hong Kong Securities Limited | C207: Overall Coordinator | D207: https://www1.hkexnews.hk/app/sehk/2025/107388/documents/sehk25060502412.pdf | E207: OC Announcement - 05/06/2025 | F207: 5 June 2025
A208: Shenzhen Hipine Precision Technology Co., Ltd. | B208: Ping An Securities (Hong Kong) Company Limited | C208: Overall Coordinator | D208: https://www1.hkexnews.hk/app/sehk/2025/107421/documents/sehk25060302776.pdf | E208: OC Announcement - 04/06/2025 | F208: 45812
A209: Hanx Biopharmaceuticals (Wuhan) Co., Ltd. | B209: ICBC International Securities Limited | C209: Sponsor-Overall Coordinator | D209: https://www1.hkexnews.hk/app/sehk/2025/107420/documents/sehk25060203419.pdf | E209: OC Announcement - 02/06/2025 | F209: 2 June 2025
A210: Hanx Biopharmaceuticals (Wuhan) Co., Ltd. | B210: CLSA Limited | C210: Overall Coordinator | D210: https://www1.hkexnews.hk/app/sehk/2025/107420/documents/sehk25060203419.pdf | E210: OC Announcement - 02/06/2025 | F210: 2 June 2025
A211: Hanx Biopharmaceuticals (Wuhan) Co., Ltd. | B211: China Securities (International) Corporate Finance Company Limited | C211: Overall Coordinator | D211: https://www1.hkexnews.hk/app/sehk/2025/107420/documents/sehk25060203419.pdf | E211: OC Announcement - 02/06/2025 | F211: 2 June 2025
A212: Hanx Biopharmaceuticals (Wuhan) Co., Ltd. | B212: China Merchants Securities (HK) Co., Limited | C212: Overall Coordinator | D212: https://www1.hkexnews.hk/app/sehk/2025/107420/documents/sehk25060203419.pdf | E212: OC Announcement - 02/06/2025 | F212: 2 June 2025
A213: Hanx Biopharmaceuticals (Wuhan) Co., Ltd. | B213: Haitong International Securities Company Limited | C213: Overall Coordinator | D213: https://www1.hkexnews.hk/app/sehk/2025/107420/documents/sehk25060203419.pdf | E213: OC Announcement - 02/06/2025 | F213: 2 June 2025
A214: Hanx Biopharmaceuticals (Wuhan) Co., Ltd. | B214: CCB International Capital Limited | C214: Overall Coordinator | D214: https://www1.hkexnews.hk/app/sehk/2025/107420/documents/sehk25060203419.pdf | E214: OC Announcement - 02/06/2025 | F214: 2 June 2025
A215: Beijing 51World Digital Twin Technology Co., Ltd. | B215: China International Capital Corporation Hong Kong Securities Limited | C215: Sponsor-Overall Coordinator | D215: https://www1.hkexnews.hk/app/sehk/2025/107417/documents/sehk25053002718.pdf | E215: OC Announcement - 30/05/2025 | F215: 30 May 2025
A216: Beijing 51World Digital Twin Technology Co., Ltd. | B216: Huatai Financial Holdings (Hong Kong) Limited | C216: Sponsor-Overall Coordinator | D216: https://www1.hkexnews.hk/app/sehk/2025/107417/documents/sehk25053002718.pdf | E216: OC Announcement - 30/05/2025 | F216: 30 May 2025
A217: Beijing 51World Digital Twin Technology Co., Ltd. | B217: CMB International Capital Limited | C217: Overall Coordinator | D217: https://www1.hkexnews.hk/app/sehk/2025/107417/documents/sehk25053002718.pdf | E217: OC Announcement - 30/05/2025 | F217: 30 May 2025
A218: Beijing 51World Digital Twin Technology Co., Ltd. | B218: China Securities (International) Corporate Finance Company Limited | C218: Overall Coordinator | D218: https://www1.hkexnews.hk/app/sehk/2025/107417/documents/sehk25053002718.pdf | E218: OC Announcement - 30/05/2025 | F218: 30 May 2025
A219: Sainte Nutritional Inc. | B219: CLSA Limited | C219: Overall Coordinator | D219: https://www1.hkexnews.hk/app/sehk/2025/107416/documents/sehk25053002638.pdf | E219: OC Announcement - 30/05/2025 | F219: 30 May 2025
A220: Shandong Kuailv Technology Development Co., Ltd. | B220: BOCOM International Securities Limited | C220: Overall Coordinator | D220: https://www1.hkexnews.hk/app/sehk/2025/107387/documents/sehk25053002516.pdf | E220: OC Announcement - 30/05/2025 | F220: 19 May 2025
... A254: Janbon High Tech Co., Ltd. | B254: China Securities (International) Corporate Finance Company Limited | C254: Overall Coordinator | D254: https://www1.hkexnews.hk/app/sehk/2025/107331/documents/sehk25051500716.pdf | E254: OC Announcement - 15/05/2025 | F254: 15 May 2025
A255: Nuobikan Artificial Intelligence Technology (Chengdu) Co., Ltd. | B255: China International Capital Corporation Hong Kong Securities Limited | C255: Sole Overall Coordinator | D255: https://www1.hkexnews.hk/app/sehk/2025/107367/documents/sehk25051401052.pdf | E255: OC Announcement - 14/05/2025 | F255: 45791
A256: Eastenova (Chengdu) Biotechnology Co., Ltd. | B256: CCB International Capital Limited | C256: Overall Coordinator | D256: https://www1.hkexnews.hk/app/sehk/2025/107366/documents/sehk25051201289.pdf | E256: OC Announcement - 12/05/2025 | F256: 12 May 2025
A257: OUR United Corporation | B257: China Securities (International) Corporate Finance Company Limited | C257: Sponsor-Overall Coordinator | D257: https://www1.hkexnews.hk/app/sehk/2025/107317/documents/sehk25051200876.pdf | E257: OC Announcement - 12/05/2025 | F257: 28 April 2025
A258: OUR United Corporation | B258: SPDB International Capital Limited | C258: Sponsor-Overall Coordinator | D258: https://www1.hkexnews.hk/app/sehk/2025/107317/documents/sehk25051200876.pdf | E258: OC Announcement - 12/05/2025 | F258: 28 April 2025
A259: OUR United Corporation | B259: CMBC Securities Company Limited | C259: Sponsor-Overall Coordinator | D259: https://www1.hkexnews.hk/app/sehk/2025/107317/documents/sehk25051200876.pdf | E259: OC Announcement - 12/05/2025 | F259: 28 April 2025
A260: OUR United Corporation | B260: CCB International Capital Limited | C260: Overall Coordinator | D260: https://www1.hkexnews.hk/app/sehk/2025/107317/documents/sehk25051200876.pdf | E260: OC Announcement - 12/05/2025 | F260: 12 May 2025
A261: OUR United Corporation | B261: CMB International Capital Limited | C261: Overall Coordinator | D261: https://www1.hkexnews.hk/app/sehk/2025/107317/documents/sehk25051200876.pdf | E261: OC Announcement - 12/05/2025 | F261: 12 May 2025
A262: OUR United Corporation | B262: DBS Asia Capital Limited | C262: Overall Coordinator | D262: https://www1.hkexnews.hk/app/sehk/2025/107317/documents/sehk25051200876.pdf | E262: OC Announcement - 12/05/2025 | F262: 12 May 2025
A263: Hangzhou Tongshifu Cultural and Creative (Group) Co., Ltd. | B263: CMB International Capital Limited | C263: Overall Coordinator | D263: https://www1.hkexnews.hk/app/sehk/2025/107350/documents/sehk25050901308.pdf | E263: OC Announcement - 09/05/2025 | F263: 9 May 2025
A264: Shanghai Fuiou Payment Service Corp., Ltd. | B264: CLSA Limited | C264: Overall Coordinator | D264: https://www1.hkexnews.hk/app/sehk/2025/107352/documents/sehk25050901500.pdf | E264: OC Announcement - 09/05/2025 | F264: 9 May 2025
A265: Shanghai Fuiou Payment Service Corp., Ltd. | B265: Shenwan Hongyuan Securities (H.K.) Limited | C265: Overall Coordinator | D265: https://www1.hkexnews.hk/app/sehk/2025/107352/documents/sehk25050901500.pdf | E265: OC Announcement - 09/05/2025 | F265: 9 May 2025
A266: Three Squirrels Inc. | B266: CLSA Limited | C266: Sponsor-Overall Coordinator | D266: https://www1.hkexnews.hk/app/sehk/2025/107311/documents/sehk25050900742.pdf | E266: OC Announcement - 09/05/2025 | F266: 25 April 2025
A267: Three Squirrels Inc. | B267: China International Capital Corporation Hong Kong Securities Limited | C267: Overall Coordinator | D267: https://www1.hkexnews.hk/app/sehk/2025/107311/documents/sehk25050900742.pdf | E267: OC Announcement - 09/05/2025 | F267: 9 May 2025
... A364: PATEO CONNECT Technology (Shanghai) Corporation | B364: CLSA Limited | C364: Overall Coordinator | D364: https://www1.hkexnews.hk/app/sehk/2025/107226/documents/sehk25032501308.pdf | E364: OC Announcement - 25/03/2025 | F364: 25 March 2025
A365: AOLG Services Group Co., Ltd | B365: ABCI Capital Limited | C365: Sole Sponsor-Overall Coordinator | D365: https://www1.hkexnews.hk/app/sehk/2025/107207/documents/sehk25032100204.pdf | E365: OC Announcement - 21/03/2025 | F365: 45736
A366: Shenzhen Longsys Electronics Co., Ltd. | B366: Citigroup Global Markets Asia Limited | C366: Overall Coordinator | D366: https://www1.hkexnews.hk/app/sehk/2025/107208/documents/sehk25032100879.pdf | E366: OC Announcement - 21/03/2025 | F366: 21 March 2025
A367: Shenzhen Longsys Electronics Co., Ltd. | B367: CLSA Limited | C367: Overall Coordinator | D367: https://www1.hkexnews.hk/app/sehk/2025/107208/documents/sehk25032100879.pdf | E367: OC Announcement - 21/03/2025 | F367: 21 March 2025
A368: Chery Automobile Co., Ltd. | B368: China International Capital Corporation Hong Kong Securities Limited | C368: Sponsor-Overall Coordinator | D368: https://www1.hkexnews.hk/app/sehk/2025/107145/documents/sehk25031400798.pdf | E368: OC Announcement - 14/03/2025 | F368: 14 March 2025
A369: Chery Automobile Co., Ltd. | B369: Huatai Financial Holdings (Hong Kong) Limited | C369: Sponsor-Overall Coordinator | D369: https://www1.hkexnews.hk/app/sehk/2025/107145/documents/sehk25031400798.pdf | E369: OC Announcement - 14/03/2025 | F369: 14 March 2025
A370: Chery Automobile Co., Ltd. | B370: GF Securities (Hong Kong) Brokerage Limited | C370: Sponsor-Overall Coordinator | D370: https://www1.hkexnews.hk/app/sehk/2025/107145/documents/sehk25031400798.pdf | E370: OC Announcement - 14/03/2025 | F370: 14 March 2025
A371: Chery Automobile Co., Ltd. | B371: CLSA Limited | C371: Overall Coordinator | D371: https://www1.hkexnews.hk/app/sehk/2025/107145/documents/sehk25031400798.pdf | E371: OC Announcement - 14/03/2025 | F371: 14 March 2025
A372: Hebei Haiwei Electronic New Material Technology Co., Ltd. | B372: China International Capital Corporation Hong Kong Securities Limited | C372: Sponsor-Overall Coordinator | D372: https://www1.hkexnews.hk/app/sehk/2025/107140/documents/sehk25031300010.pdf | E372: OC Announcement - 13/03/2025 | F372: 26 February 2025
A373: Hebei Haiwei Electronic New Material Technology Co., Ltd. | B373: CLSA Limited | C373: Overall Coordinator | D373: https://www1.hkexnews.hk/app/sehk/2025/107140/documents/sehk25031300010.pdf | E373: OC Announcement - 13/03/2025 | F373: 13 March 2025
A374: Hebei Haiwei Electronic New Material Technology Co., Ltd. | B374: China Securities (International) Corporate Finance Company Limited | C374: Overall Coordinator | D374: https://www1.hkexnews.hk/app/sehk/2025/107140/documents/sehk25031300010.pdf | E374: OC Announcement - 13/03/2025 | F374: 13 March 2025
A375: Solarspace Technology Co., Ltd. | B375: China Securities (International) Corporate Finance Company Limited | C375: Overall Coordinator | D375: https://www1.hkexnews.hk/app/sehk/2025/107187/documents/sehk25031301548.pdf | E375: OC Announcement - 13/03/2025 | F375: 13 March 2025
A376: Solarspace Technology Co., Ltd. | B376: Corporate Finance Company Limited | C376: Overall Coordinator | D376: https://www1.hkexnews.hk/app/sehk/2025/107187/documents/sehk25031301548.pdf | E376: OC Announcement - 13/03/2025 | F376: 13 March 2025
A377: Solarspace Technology Co., Ltd. | B377: CLSA Limited | C377: Overall Coordinator | D377: https://www1.hkexnews.hk/app/sehk/2025/107187/documents/sehk25031301548.pdf | E377: OC Announcement - 13/03/2025 | F377: 13 March 2025
... A402: Huge Dental Limited | B402: Daiwa Capital Markets Hong Kong Limited | C402: Overall Coordinator | D402: https://www1.hkexnews.hk/app/sehk/2025/107132/documents/sehk25022801330.pdf | E402: OC Announcement - 28/02/2025 | F402: 28 February 2025
A403: Seyond Holdings Ltd. | B403: China Securities (International) Corporate Finance Company Limited | C403: Overall Coordinator | D403: https://www1.hkexnews.hk/app/sehk/2025/107128/documents/sehk25022600830.pdf | E403: OC Announcement - 26/02/2025 | F403: 45700
A404: Seyond Holdings Ltd. | B404: Zero2IPO Securities Limited | C404: Overall Coordinator | D404: https://www1.hkexnews.hk/app/sehk/2025/107128/documents/sehk25022600830.pdf | E404: OC Announcement - 26/02/2025 | F404: 45714
A405: Seyond Holdings Ltd. | B405: CLSA Limited | C405: Overall Coordinator | D405: https://www1.hkexnews.hk/app/sehk/2025/107128/documents/sehk25022600830.pdf | E405: OC Announcement - 26/02/2025 | F405: 45714
A406: Wuxi Lead Intelligent Equipment Co., Ltd. | B406: CLSA Limited | C406: Overall Coordinator | D406: https://www1.hkexnews.hk/app/sehk/2025/107139/documents/sehk25022500578.pdf | E406: OC Announcement - 25/02/2025 | F406: 25 February 2025
A407: Wuxi Lead Intelligent Equipment Co., Ltd. | B407: J.P. Morgan Securities (Asia Pacific) Limited | C407: Overall Coordinator | D407: https://www1.hkexnews.hk/app/sehk/2025/107139/documents/sehk25022500578.pdf | E407: OC Announcement - 25/02/2025 | F407: 25 February 2025
A408: Sigenergy Technology Co., Ltd. | B408: CLSA Limited | C408: Overall Coordinator | D408: https://www1.hkexnews.hk/app/sehk/2025/107134/documents/sehk25022101034.pdf | E408: OC Announcement - 21/02/2025 | F408: 21 February 2025
A409: Sigenergy Technology Co., Ltd. | B409: BNP Paribas Securities (Asia) Limited | C409: Overall Coordinator | D409: https://www1.hkexnews.hk/app/sehk/2025/107134/documents/sehk25022101034.pdf | E409: OC Announcement - 21/02/2025 | F409: 21 February 2025
A410: Manycore Tech Inc. | B410: J.P. Morgan Securities (Asia Pacific) Limited | C410: Overall Coordinator | D410: https://www1.hkexnews.hk/app/sehk/2025/107129/documents/sehk25021401102.pdf | E410: OC Announcement - 14/02/2025 | F410: 14 February 2025
A411: Manycore Tech Inc. | B411: CCB International Capital Limited | C411: Overall Coordinator | D411: https://www1.hkexnews.hk/app/sehk/2025/107129/documents/sehk25021401102.pdf | E411: OC Announcement - 14/02/2025 | F411: 14 February 2025
A412: USAS Building System (Shanghai) Co., Ltd. | B412: Shenwan Hongyuan Securities (H.K.) Limited | C412: Overall Coordinator | D412: https://www1.hkexnews.hk/app/sehk/2025/107130/documents/sehk25021401440.pdf | E412: OC Announcement - 14/02/2025 | F412: 14 February 2025
A413: Vigonvita Life Sciences Co., Ltd. | B413: CLSA Limited | C413: Sponsor-Overall Coordinator | D413: https://www1.hkexnews.hk/app/sehk/2025/107116/documents/sehk25021100186.pdf | E413: OC Announcement - 11/02/2025 | F413: 11 February 2025
A414: Vigonvita Life Sciences Co., Ltd. | B414: China International Capital Corporation Hong Kong Securities Limited | C414: Overall Coordinator | D414: https://www1.hkexnews.hk/app/sehk/2025/107116/documents/sehk25021100186.pdf | E414: OC Announcement - 11/02/2025 | F414: 11 February 2025
A415: Vigonvita Life Sciences Co., Ltd. | B415: ABCI Capital Limited | C415: Overall Coordinator | D415: https://www1.hkexnews.hk/app/sehk/2025/107116/documents/sehk25021100186.pdf | E415: OC Announcement - 11/02/2025 | F415: 11 February 2025
A416: Vigonvita Life Sciences Co., Ltd. | B416: China Galaxy International Securities (Hong Kong) Co., Limited | C416: Overall Coordinator | D416: https://www1.hkexnews.hk/app/sehk/2025/107116/documents/sehk25021100186.pdf | E416: OC Announcement - 11/02/2025 | F416: 11 February 2025
A417: Adaspace Technology Co., Ltd. | B417: CCB International Capital Limited | C417: Overall Coordinator | D417: https://www1.hkexnews.hk/app/sehk/2025/107117/documents/sehk25021001020.pdf | E417: OC Announcement - 10/02/2025 | F417: 10 February 2025
... A449: Innovation Global Industries Holdings Limited | B449: China International Capital Corporation Hong Kong Securities Limited | C449: Overall Coordinator | D449: https://www1.hkexnews.hk/app/sehk/2025/107088/documents/sehk25011301047.pdf | E449: OC Announcement - 13/01/2025 | F449: 13 January 2025
A450: Innovation Global Industries Holdings Limited | B450: Huatai Financial Holdings (Hong Kong) Limited | C450: Overall Coordinator | D450: https://www1.hkexnews.hk/app/sehk/2025/107088/documents/sehk25011301047.pdf | E450: OC Announcement - 12/01/2025 | F450: 45669
A451: Coland Ocean Group Limited | B451: Yue Xiu Capital Limited | C451: Overall Coordinator | D451: https://www1.hkexnews.hk/app/sehk/2025/107086/documents/sehk25011200158.pdf | E451: OC Announcement - 12/01/2025 | F451: 45669
A454: 174

Sheet Bank Rankings
A1: Bank | B1: Total Mandates | C1: Sponsor Roles | D1: Lead Rate % | E1: Market Share %
A2: Shanxi Securities International Limited | B2: =COUNTIF(RawData!B:B,A2) -> 1 | C2: =COUNTIFS(RawData!B:B,A2,RawData!C:C,"*Sponsor*") -> 0 | D2: =IF(B2=0,0,C2/B2) -> 0 | E2: =B2/(COUNTA(RawData!A:A)-1) -> 0.0022172949
A3: Zero2IPO Securities Limited | B3: =COUNTIF(RawData!B:B,A3) -> 1 | C3: =COUNTIFS(RawData!B:B,A3,RawData!C:C,"*Sponsor*") -> 0 | D3: =IF(B3=0,0,C3/B3) -> 0 | E3: =B3/(COUNTA(RawData!A:A)-1) -> 0.0022172949
A4: ABCI Capital Limited | B4: =COUNTIF(RawData!B:B,A4) -> 19 | C4: =COUNTIFS(RawData!B:B,A4,RawData!C:C,"*Sponsor*") -> 5 | D4: =IF(B4=0,0,C4/B4) -> 0.26315789 | E4: =B4/(COUNTA(RawData!A:A)-1) -> 0.042128603
A5: BNP Paribas Securities (Asia) Limited | B5: =COUNTIF(RawData!B:B,A5) -> 5 | C5: =COUNTIFS(RawData!B:B,A5,RawData!C:C,"*Sponsor*") -> 2 | D5: =IF(B5=0,0,C5/B5) -> 0.4 | E5: =B5/(COUNTA(RawData!A:A)-1) -> 0.011086475
A6: BOCI Asia Limited | B6: =COUNTIF(RawData!B:B,A6) -> 10 | C6: =COUNTIFS(RawData!B:B,A6,RawData!C:C,"*Sponsor*") -> 1 | D6: =IF(B6=0,0,C6/B6) -> 0.1 | E6: =B6/(COUNTA(RawData!A:A)-1) -> 0.022172949
A7: BOCOM International Securities Limited | B7: =COUNTIF(RawData!B:B,A7) -> 5 | C7: =COUNTIFS(RawData!B:B,A7,RawData!C:C,"*Sponsor*") -> 1 | D7: =IF(B7=0,0,C7/B7) -> 0.2 | E7: =B7/(COUNTA(RawData!A:A)-1) -> 0.011086475
A8: CCB International Capital Limited | B8: =COUNTIF(RawData!B:B,A8) -> 24 | C8: =COUNTIFS(RawData!B:B,A8,RawData!C:C,"*Sponsor*") -> 1 | D8: =IF(B8=0,0,C8/B8) -> 0.041666667 | E8: =B8/(COUNTA(RawData!A:A)-1) -> 0.053215078
A9: CLSA Limited | B9: =COUNTIF(RawData!B:B,A9) -> 69 | C9: =COUNTIFS(RawData!B:B,A9,RawData!C:C,"*Sponsor*") -> 22 | D9: =IF(B9=0,0,C9/B9) -> 0.31884058 | E9: =B9/(COUNTA(RawData!A:A)-1) -> 0.15299335
A10: CMB International Capital Limited | B10: =COUNTIF(RawData!B:B,A10) -> 27 | C10: =COUNTIFS(RawData!B:B,A10,RawData!C:C,"*Sponsor*") -> 3 | D10: =IF(B10=0,0,C10/B10) -> 0.11111111 | E10: =B10/(COUNTA(RawData!A:A)-1) -> 0.059866962
A11: CMBC Securities Company Limited | B11: =COUNTIF(RawData!B:B,A11) -> 6 | C11: =COUNTIFS(RawData!B:B,A11,RawData!C:C,"*Sponsor*") -> 2 | D11: =IF(B11=0,0,C11/B11) -> 0.33333333 | E11: =B11/(COUNTA(RawData!A:A)-1) -> 0.013303769
A12: China Everbright Securities (HK) Limited | B12: =COUNTIF(RawData!B:B,A12) -> 2 | C12: =COUNTIFS(RawData!B:B,A12,RawData!C:C,"*Sponsor*") -> 1 | D12: =IF(B12=0,0,C12/B12) -> 0.5 | E12: =B12/(COUNTA(RawData!A:A)-1) -> 0.0044345898
A13: China Galaxy International Securities (Hong Kong) Co., Limited | B13: =COUNTIF(RawData!B:B,A13) -> 7 | C13: =COUNTIFS(RawData!B:B,A13,RawData!C:C,"*Sponsor*") -> 0 | D13: =IF(B13=0,0,C13/B13) -> 0 | E13: =B13/(COUNTA(RawData!A:A)-1) -> 0.015521064
... A59: Zhongtai International Securities Limited | B59: =COUNTIF(RawData!B:B,A59) -> 4 | C59: =COUNTIFS(RawData!B:B,A59,RawData!C:C,"*Sponsor*") -> 0 | D59: =IF(B59=0,0,C59/B59) -> 0 | E59: =B59/(COUNTA(RawData!A:A)-1) -> 0.0088691796
A62: Note: Sort by 'Total Mandates' column to see most active banks

Sheet Key Banks Analysis
A1: KEY BANKS PARTNERSHIP ANALYSIS
A3: Huatai
A4: Total Deals: | B4: =COUNTIF(RawData!B:B,"Huatai Financial Holdings (Hong Kong) Limited") -> 29
A5: As Sponsor: | B5: =COUNTIFS(RawData!B:B,"Huatai Financial Holdings (Hong Kong) Limited",RawData!C:C,"*Sponsor*") -> 10
A7: Top Partners:
A8: China International Capital Corporation Hong Kong Securities Limited | B8: 12 | C8: deals together
A9: CLSA Limited | B9: 9 | C9: deals together
A10: ABCI Capital Limited | B10: 5 | C10: deals together
A11: CCB International Capital Limited | B11: 5 | C11: deals together
A12: GF Securities (Hong Kong) Brokerage Limited | B12: 5 | C12: deals together
A15: Morgan Stanley
A16: Total Deals: | B16: =COUNTIF(RawData!B:B,"Morgan Stanley Asia Limited") -> 4
A17: As Sponsor: | B17: =COUNTIFS(RawData!B:B,"Morgan Stanley Asia Limited",RawData!C:C,"*Sponsor*") -> 1
A19: Top Partners:
A20: ABCI Capital Limited | B20: 2 | C20: deals together
A21: Huatai Financial Holdings (Hong Kong) Limited | B21: 2 | C21: deals together
A22: CLSA Limited | B22: 2 | C22: deals together
A23: BOCI Asia Limited | B23: 1 | C23: deals together
A24: Deutsche Bank AG | B24: 1 | C24: deals together
A27: Bank of America/Merrill Lynch
A28: Total Deals: | B28: =COUNTIF(RawData!B:B,"Merrill Lynch (Asia Pacific) Limited") -> 2
A29: As Sponsor: | B29: =COUNTIFS(RawData!B:B,"Merrill Lynch (Asia Pacific) Limited",RawData!C:C,"*Sponsor*") -> 0
A31: Top Partners:
A32: Haitong International Securities Company Limited | B32: 1 | C32: deals together
A33: UBS AG Hong Kong Branch | B33: 1 | C33: deals together
A34: Huatai Financial Holdings (Hong Kong) Limited | B34: 1 | C34: deals together
A35: Goldman Sachs (Asia) L.L.C. | B35: 1 | C35: deals together
A36: J.P. Morgan Securities (Asia Pacific) Limited | B36: 1 | C36: deals together
A39: STRATEGIC INSIGHTS:
A41: • ABCI Capital works with both Huatai (5 deals) and Morgan Stanley (2 deals) - potential bridge
A42: • CLSA and CICC dominate the market with 127 combined mandates (28% market share)
A43: • Huatai's strongest partnership is with CICC (12 deals) - leverage this relationship
A44: • Morgan Stanley and Bank of America have limited presence - opportunity for growth
A45: • 'Sponsor' roles indicate leadership position - 23% of all roles

Sheet Partnership Matrix
A1: RECURRING PARTNERSHIPS (3+ DEALS)
A3: Bank 1 | B3: Bank 2 | C3: Deal Count | D3: Key Bank Involved
A4: CLSA Limited | B4: China International Capital Corporation Hong Kong Securities Limited | C4: 19
A5: CLSA Limited | B5: CMB International Capital Limited | C5: 13
A6: China International Capital Corporation Hong Kong Securities Limited | B6: Huatai Financial Holdings (Hong Kong) Limited | C6: 12 | D6: Huatai
A7: CMB International Capital Limited | B7: China International Capital Corporation Hong Kong Securities Limited | C7: 10
A8: CLSA Limited | B8: Huatai Financial Holdings (Hong Kong) Limited | C8: 9 | D8: Huatai
A9: CLSA Limited | B9: GF Securities (Hong Kong) Brokerage Limited | C9: 8
A10: CLSA Limited | B10: Haitong International Securities Company Limited | C10: 7
A11: CCB International Capital Limited | B11: CLSA Limited | C11: 7
A12: ABCI Capital Limited | B12: CLSA Limited | C12: 6
A13: China International Capital Corporation Hong Kong Securities Limited | B13: GF Securities (Hong Kong) Brokerage Limited | C13: 6
A14: ABCI Capital Limited | B14: CCB International Capital Limited | C14: 6
A15: CLSA Limited | B15: Guotai Junan Securities (Hong Kong) Limited | C15: 6
A16: CLSA Limited | B16: China Securities (International) Corporate Finance Company Limited | C16: 6
A17: China International Capital Corporation Hong Kong Securities Limited | B17: Deutsche Bank AG, Hong Kong Branch | C17: 6
A18: CLSA Limited | B18: Deutsche Bank AG, Hong Kong Branch | C18: 5
A19: ABCI Capital Limited | B19: Huatai Financial Holdings (Hong Kong) Limited | C19: 5 | D19: Huatai
A20: CCB International Capital Limited | B20: Huatai Financial Holdings (Hong Kong) Limited | C20: 5 | D20: Huatai
A21: GF Securities (Hong Kong) Brokerage Limited | B21: Huatai Financial Holdings (Hong Kong) Limited | C21: 5 | D21: Huatai
A22: CMB International Capital Limited | B22: China Securities (International) Corporate Finance Company Limited | C22: 5
A23: China International Capital Corporation Hong Kong Securities Limited | B23: China Merchants Securities (HK) Co., Limited | C23: 4
